{ "_id" : { "$oid" : "5e8988d0ad296d176c4c6c51" }, "videoid" : { "$oid" : "5e887802e0a55928df19da47" }, "from" : { "$oid" : "5e88a497812ea5436b9d7f62" }, "to" : { "$oid" : "5e85f463c823f35abda13c30" }, "commentinfo" : "222", "parentid" : "5e8988c5ad296d176c4c6c50", "createtime" : { "$date" : "2020-04-05T07:29:20.986+0000" }, "__v" : 0 }
{ "_id" : { "$oid" : "5e89a6a6ad296d176c4c6c54" }, "videoid" : { "$oid" : "5e887807e0a55928df19da48" }, "from" : { "$oid" : "5e88a497812ea5436b9d7f62" }, "to" : { "$oid" : "5e85f463c823f35abda13c30" }, "commentinfo" : "123", "parentid" : "5e89a68aad296d176c4c6c53", "createtime" : { "$date" : "2020-04-05T09:36:38.073+0000" }, "__v" : 0 }
{ "_id" : { "$oid" : "5e8c92320efcc50e7caf7c7e" }, "videoid" : { "$oid" : "5e8c8f840efcc50e7caf7c79" }, "from" : { "$oid" : "5e85f463c823f35abda13c30" }, "to" : { "$oid" : "5e85f463c823f35abda13c30" }, "commentinfo" : "123", "parentid" : "5e8c8fa00efcc50e7caf7c7b", "createtime" : { "$date" : "2020-04-07T14:46:10.274+0000" }, "__v" : 0 }
